engiyn_core/__init__.py
engiyn_core-0.1.2.dist-info/licenses/LICENSE
engiyn_core-0.1.2.dist-info/METADATA
engiyn_core-0.1.2.dist-info/WHEEL
engiyn_core-0.1.2.dist-info/top_level.txt
engiyn_core-0.1.2.dist-info/RECORD
