Metadata-Version: 2.4
Name: engiyn-core
Version: 0.1.2
Summary: Engiyn Core - Multi-cloud, AI/IDE integration engine
Home-page: https://github.com/ledyardco/engiyn-core
Author: Ledyardco
Author-email: info@ledyardco.com
Classifier: Development Status :: 3 - Alpha
Classifier: Intended Audience :: Developers
Classifier: License :: OSI Approved :: MIT License
Classifier: Programming Language :: Python :: 3
Classifier: Programming Language :: Python :: 3.7
Classifier: Programming Language :: Python :: 3.8
Classifier: Programming Language :: Python :: 3.9
Requires-Python: >=3.7
License-File: LICENSE
Requires-Dist: jsonschema
Requires-Dist: flask
Requires-Dist: click
Dynamic: author
Dynamic: author-email
Dynamic: classifier
Dynamic: home-page
Dynamic: license-file
Dynamic: requires-dist
Dynamic: requires-python
Dynamic: summary
